pdat_aes_encryptor/aes_encryptor.py
pdat_aes_encryptor-0.3.0.dist-info/LICENSE
pdat_aes_encryptor-0.3.0.dist-info/METADATA
pdat_aes_encryptor-0.3.0.dist-info/WHEEL
pdat_aes_encryptor-0.3.0.dist-info/RECORD
