Metadata-Version: 2.1
Name: pdat-aes-encryptor
Version: 0.3.0
Summary: AES Encryptor
License: MIT
Keywords: aes,encryptor
Author: Pavel Dat
Author-email: dats.pavel1999@gmail.com
Requires-Python: >=3.10,<4.0
Classifier: License :: OSI Approved :: MIT License
Classifier: Programming Language :: Python :: 3
Classifier: Programming Language :: Python :: 3.10
Classifier: Programming Language :: Python :: 3.11
Classifier: Programming Language :: Python :: 3.12
Classifier: Programming Language :: Python :: 3.13
Requires-Dist: cryptography (>=43.0.1,<44.0.0)
Requires-Dist: loguru (>=0.7.2,<0.8.0)
